{
  "project_info": {
    "project_number": "595242001706",
    "firebase_url": "https://embonics-8b782-default-rtdb.firebaseio.com",
    "project_id": "embonics-8b782",
    "storage_bucket": "embonics-8b782.appspot.com"
  },
  "client": [
    {
      "client_info": {
        "mobilesdk_app_id": "1:595242001706:android:734fa22dd8866dab0daa53",
        "android_client_info": {
          "package_name": "com.example.embonics"
        }
      },
      "oauth_client": [],
      "api_key": [
        {
          "current_key": "AIzaSyBvz0EJYNym_OB6A9FuxwXEVfERQ4BdHIk"
        }
      ],
      "services": {
        "appinvite_service": {
          "other_platform_oauth_client": []
        }
      }
    }
  ],
  "configuration_version": "1"
}